easyOpenWeather/__init__.py
easyOpenWeather/module.py
easyOpenWeather-0.22.dist-info/LICENSE
easyOpenWeather-0.22.dist-info/METADATA
easyOpenWeather-0.22.dist-info/WHEEL
easyOpenWeather-0.22.dist-info/top_level.txt
easyOpenWeather-0.22.dist-info/RECORD
