Metadata-Version: 2.1
Name: easyOpenWeather
Version: 0.22
Summary: Get the weather of any city instantly in your project
Home-page: https://github.com/harshnative/easyOpenWeather_Module
Author: Harsh Native
Author-email: Harshnative@gmail.com
License: UNKNOWN
Platform: UNKNOWN
Classifier: Programming Language :: Python :: 3
Classifier: License :: OSI Approved :: MIT License
Classifier: Operating System :: OS Independent
Requires-Python: >=3.6
